featurestoresdk/__init__.py
featurestoresdk/feature_store_sdk.py
featurestoresdk/sdk_exception.py
featurestoresdk/singleton_manager.py
featurestoresdk/config/config.json
featurestoresdk-0.3.1.dist-info/licenses/LICENSES.txt
featurestoresdk-0.3.1.dist-info/METADATA
featurestoresdk-0.3.1.dist-info/WHEEL
featurestoresdk-0.3.1.dist-info/top_level.txt
featurestoresdk-0.3.1.dist-info/RECORD
