Metadata-Version: 2.4
Name: featurestoresdk
Version: 0.3.1
Summary: feature store SDK for Training Host
Home-page: https://gerrit.o-ran-sc.org/r/admin/repos/aiml-fw/athp/sdk/feature-store,general
Author: Joseph Thaliath
Author-email: O-RAN Software Community <discuss@lists.o-ran-sc.org>
License: Apache 2.0
Project-URL: Homepage, https://gerrit.o-ran-sc.org/r/admin/repos/aiml-fw/athp/sdk/feature-store,general
Project-URL: Repository, https://gerrit.o-ran-sc.org/r/admin/repos/aiml-fw/athp/sdk/feature-store,general
Classifier: Programming Language :: Python :: 3
Classifier: License :: OSI Approved :: Apache Software License
Classifier: Operating System :: OS Independent
Requires-Python: >=3.10
License-File: LICENSES.txt
Requires-Dist: pandas
Requires-Dist: cassandra-driver==3.25.0
Requires-Dist: kubernetes
Provides-Extra: test
Requires-Dist: pytest; extra == "test"
Requires-Dist: coverage; extra == "test"
Requires-Dist: pytest-cov; extra == "test"
Requires-Dist: mock; extra == "test"
Dynamic: author
Dynamic: home-page
Dynamic: license-file
